pyergo/__init__.py
pyergo/damage_models/__init__.py
pyergo/damage_models/barrett_callaghan.py
pyergo/damage_models/base.py
pyergo/damage_models/lifft.py
pyergo/damage_models/miner_palmgren.py
pyergo/utils/__init__.py
pyergo/utils/units.py
pyergo-0.1.3.dist-info/METADATA
pyergo-0.1.3.dist-info/WHEEL
pyergo-0.1.3.dist-info/top_level.txt
pyergo-0.1.3.dist-info/RECORD
