Metadata-Version: 2.4
Name: pyergo
Version: 0.1.3
Summary: A lightweight ergonomics python library
Requires-Python: >=3.9
Requires-Dist: numpy>=2.0.2
Requires-Dist: scipy>=1.13.1
Provides-Extra: test
Requires-Dist: pytest>=8.4.2; extra == "test"
